setup.cfg
setup.py
kdic_project/__init__.py
kdic_project/__main__.py
kdic_project.egg-info/PKG-INFO
kdic_project.egg-info/SOURCES.txt
kdic_project.egg-info/dependency_links.txt
kdic_project.egg-info/entry_points.txt
kdic_project.egg-info/requires.txt
kdic_project.egg-info/top_level.txt