Metadata-Version: 1.0
Name: kdic-project
Version: 0.0.2
Summary: A simple search in dictionary sizte on terminal for Korean
Home-page: http://www.coupang.com
Author: sonic
Author-email: ultrakain@gmail.com
License: MIT
Keywords: simple english dictionary korean
Platform: UNKNOWN
